MANIFEST.in
README.md
setup.py
aurum/__init__.py
aurum/au.py
aurum/base.py
aurum/code_tracker.py
aurum/commands.py
aurum/constants.py
aurum/dataset_tracker.py
aurum/dry_run.py
aurum/env_builder.py
aurum/experiment_parser.py
aurum/git.py
aurum/gitignore_template.txt
aurum/lock_file.py
aurum/logging_tracker.py
aurum/package_tracker.py
aurum/singleton.py
aurum/theorem.py
aurum/time_tracker.py
aurum/utils.py
aurum.egg-info/PKG-INFO
aurum.egg-info/SOURCES.txt
aurum.egg-info/dependency_links.txt
aurum.egg-info/entry_points.txt
aurum.egg-info/requires.txt
aurum.egg-info/top_level.txt
aurum/metadata/__init__.py
aurum/metadata/code.py
aurum/metadata/dataset.py
aurum/metadata/experiment.py
aurum/metadata/metadata.py
aurum/metadata/metrics.py
aurum/metadata/parameters.py
aurum/metadata/requirements.py
aurum/metadata/weights.py